simple_locations/__init__.py
simple_locations/admin.py
simple_locations/api.py
simple_locations/feature_manager.py
simple_locations/fixtures/initial_data.json
simple_locations/forms.py
simple_locations/gis_functions.py
simple_locations/locale/fr/LC_MESSAGES/django.po
simple_locations/management/__init__.py
simple_locations/management/commands/__init__.py
simple_locations/management/commands/create_borders.py
simple_locations/management/commands/create_projected_areas.py
simple_locations/management/commands/dump_locations.py
simple_locations/management/commands/import_dird.py
simple_locations/manager.py
simple_locations/migrations/0001_initial.py
simple_locations/migrations/0002_load_initial_data.py
simple_locations/migrations/0003_auto_20170320_1024.py
simple_locations/migrations/0004_auto_20170330_1618.py
simple_locations/migrations/0005_auto_20170403_1507.py
simple_locations/migrations/0006_auto_20180202_1540.py
simple_locations/migrations/0007_area_geom_can_be_blank.py
simple_locations/migrations/0008_auto_20200804_0554.py
simple_locations/migrations/0009_auto_20211111_0805.py
simple_locations/migrations/0010_add_border_model.py
simple_locations/migrations/0011_denormed_border_fields.py
simple_locations/migrations/0012_auto_20220221_0817.py
simple_locations/migrations/0013_auto_20220307_0618.py
simple_locations/migrations/__init__.py
simple_locations/model_schemas.py
simple_locations/models.py
simple_locations/models.pyi
simple_locations/requirements.in
simple_locations/router.py
simple_locations/schemas.py
simple_locations/settings.py
simple_locations/static/css/tree-default-line.gif
simple_locations/static/css/tree.css
simple_locations/static/images/ajax-loader.gif
simple_locations/static/images/delete.png
simple_locations/static/images/edit.png
simple_locations/static/images/minus.gif
simple_locations/static/images/plus.gif
simple_locations/static/images/tree-default-line.gif
simple_locations/static/javascripts/simple_locations.js
simple_locations-4.0.0.dist-info/WHEEL
simple_locations-4.0.0.dist-info/METADATA
simple_locations-4.0.0.dist-info/RECORD
