Metadata-Version: 2.1
Name: simple-locations
Version: 4.0.0
Summary: The common location package for Catalpa's projects
Home-page: https://github.com/catalpainternational/simple_locations
License: BSD
Author: Joshua Brooks
Author-email: josh@catalpa.io
Requires-Python: >=3.8,<4.0
Classifier: License :: Other/Proprietary License
Classifier: Programming Language :: Python :: 3
Classifier: Programming Language :: Python :: 3.8
Classifier: Programming Language :: Python :: 3.9
Classifier: Programming Language :: Python :: 3.10
Classifier: Programming Language :: Python :: 3.11
Requires-Dist: django-geojson (>=4.0.0,<5.0.0)
Requires-Dist: django-mptt (>=0.14.0,<0.15.0)
Requires-Dist: django-ninja (>=0.21.0,<0.22.0)
Requires-Dist: pydantic (>=1.10.6,<2.0.0)
Project-URL: Repository, https://github.com/catalpainternational/simple_locations
